NecessaryConditionAnalysis/__init__.py
NecessaryConditionAnalysis/main.py
NecessaryConditionAnalysis-0.1.1.dist-info/LICENCE
NecessaryConditionAnalysis-0.1.1.dist-info/METADATA
NecessaryConditionAnalysis-0.1.1.dist-info/WHEEL
NecessaryConditionAnalysis-0.1.1.dist-info/top_level.txt
NecessaryConditionAnalysis-0.1.1.dist-info/RECORD
