Metadata-Version: 2.1
Name: NecessaryConditionAnalysis
Version: 0.1.1
Summary: Necessary Condition Analysis in Python
Author-email: Ricardo Chavelas Manzo <R.ChavelasManzo@tilburguniversity.edu>
Classifier: Programming Language :: Python :: 3
Classifier: License :: OSI Approved :: MIT License
Classifier: Operating System :: OS Independent
Requires-Python: >=3.8
License-File: LICENCE
Requires-Dist: pandas >=2.0
Requires-Dist: numpy >=1.25
Requires-Dist: matplotlib >=3.7
